Metadata-Version: 2.1
Name: uuidwithdatetime
Version: 1.0.3
Summary: A package to generate a random UUID with the current date and time.
Home-page: https://github.com/Manikandanpythonjs/pythonuuiddate
Author: Manikandan AL
Author-email: manipythonjs@gmail.com
Classifier: Programming Language :: Python :: 3
Classifier: License :: OSI Approved :: MIT License
Classifier: Operating System :: OS Independent
Requires-Python: >=3.6
License-File: LICENSE
